<set id="3daf84ca581d4070a067215a00f8cf92" source-language="eng" target-language="kaz"><seg id="1" doc-id="e61ade7548224e42874dd2db756dddba" hide-source="None"><source>President Nursultan Nazarbayev Attends Don Quixote Ballet at the Kulyash Baiseitova Opera and Ballet Theater.</source>

<translation system="Apertium" type="simple" fill=";;;;" keys="Мемлекет;атындағы;балет;балетін;тамашалады">бүгін { } басшысы Нұрсұлтан Назарбаев Байсейітова { } ұлттық опера және { } театрында болып, "Дон Кихот" { } { }.</translation></seg>
<seg id="2" doc-id="e61ade7548224e42874dd2db756dddba" hide-source="None"><source>the President expressed confidence that the considerable experience gained over the past years by Milos Zeman will give a significant impetus to the development and prosperity of his country.</source>

<translation system="Apertium" type="simple" fill=";;;;" keys="Мемлекет;жылдар;жинаған;елінің;беретініне">{ } басшысы Земанның { } бойы { } мол тәжірибесі оның { } өсіп-өркендеуіне айтарлықтай серпін { } сенім білдірген.</translation></seg>
<seg id="3" doc-id="e61ade7548224e42874dd2db756dddba" hide-source="None"><source>President Nursultan Nazarbayev has sent a telegram of condolences to President of the Federative Republic of Brazil Dilma Rousseff following the fire in the city of Santa Maria that caused numerous human losses.</source>

<translation system="Apertium" type="simple" fill=";;;;;;" keys="Президенті;Республикасының;Президенті;қаласындағы;қазаға;көңіл;жолдады">Қазақстан Республикасының { } Нұрсұлтан Назарбаев Бразилия Федеративтік { } { } Дилма Руссеффке Санта-Мария { } көп адамды { } ұшыратқан өртке байланысты { } айту жеделхатын { }.</translation></seg></set>